databricks_formatter.py
databricks_sdk_utils.py
main.py
iflow_mcp_databricks-0.1.2.dist-info/licenses/LICENSE
iflow_mcp_databricks-0.1.2.dist-info/METADATA
iflow_mcp_databricks-0.1.2.dist-info/WHEEL
iflow_mcp_databricks-0.1.2.dist-info/entry_points.txt
iflow_mcp_databricks-0.1.2.dist-info/top_level.txt
iflow_mcp_databricks-0.1.2.dist-info/RECORD
