Metadata-Version: 2.4
Name: iflow-mcp_databricks
Version: 0.1.2
Summary: Databricks MCP Server for Unity Catalog exploration and SQL execution
Requires-Python: >=3.10
License-File: LICENSE
Requires-Dist: httpx>=0.28.1
Requires-Dist: mcp[cli]>=1.3.0
Requires-Dist: databricks-sdk==0.55.0
Requires-Dist: python-dotenv>=1.0.0
Dynamic: license-file
